mcp_server_monitor/__init__.py
mcp_server_monitor/__main__.py
mcp_server_monitor/server.py
mcp_server_monitor/config/__init__.py
mcp_server_monitor/config/logger.py
mcp_server_monitor/core/__init__.py
mcp_server_monitor/core/inspector.py
mcp_server_monitor/core/ssh_manager.py
mcp_server_monitor/models/__init__.py
mcp_server_monitor/models/schemas.py
mcp_server_monitor/tools/__init__.py
mcp_server_monitor/tools/docker_tools.py
mcp_server_monitor/tools/network_tools.py
mcp_server_monitor/tools/security_tools.py
mcp_server_monitor/tools/system_tools.py
mcp_server_monitor/tools/utils.py
mcp_server_monitor/utils/__init__.py
mcp_server_monitor/utils/decorators.py
mcp_server_monitor-0.1.1.dist-info/METADATA
mcp_server_monitor-0.1.1.dist-info/WHEEL
mcp_server_monitor-0.1.1.dist-info/top_level.txt
mcp_server_monitor-0.1.1.dist-info/RECORD
